[
  {
    "url": "https://github.com/ElementsProject/lightning/issues/3207",
    "publishedAt": "2019-10-25T18:58:14Z",
    "title": "Plugin notification for when UTXOs are spent?",
    "labels": [
      "feature",
      "good first issue",
      "plugin"
    ],
    "imageUrl": "https://avatars.githubusercontent.com/u/12729539?v=4"
  },
  {
    "url": "https://github.com/ElementsProject/lightning/issues/3209",
    "publishedAt": "2019-10-25T19:03:25Z",
    "title": "Pass daemon errors back to RPC handler",
    "labels": [
      "json-rpc",
      "feature",
      "good first issue"
    ],
    "imageUrl": "https://avatars.githubusercontent.com/u/12729539?v=4"
  },
  {
    "url": "https://github.com/ElementsProject/lightning/issues/3270",
    "publishedAt": "2019-11-18T14:47:18Z",
    "title": "Setting manual channel closure fee (question)",
    "labels": [
      "feature",
      "good first issue"
    ],
    "imageUrl": "https://avatars.githubusercontent.com/u/12729539?v=4"
  },
  {
    "url": "https://github.com/ElementsProject/lightning/issues/3505",
    "publishedAt": "2020-02-11T15:17:46Z",
    "title": "cleanup: Use the `-rpcwait` when waiting for bitcoind to warm up",
    "labels": [
      "cleanup",
      "good first issue"
    ],
    "imageUrl": "https://avatars.githubusercontent.com/u/12729539?v=4"
  },
  {
    "url": "https://github.com/ElementsProject/lightning/issues/3542",
    "publishedAt": "2020-02-21T19:01:42Z",
    "title": "feature request: config option to change default fundchannel feerate",
    "labels": [
      "good first issue"
    ],
    "imageUrl": "https://avatars.githubusercontent.com/u/12729539?v=4"
  },
  {
    "url": "https://github.com/ElementsProject/lightning/issues/3662",
    "publishedAt": "2020-04-23T17:00:08Z",
    "title": "Add new notifications for plugins",
    "labels": [
      "feature",
      "good first issue",
      "plugin",
      "Feature Request"
    ],
    "imageUrl": "https://avatars.githubusercontent.com/u/12729539?v=4"
  },
  {
    "url": "https://github.com/ElementsProject/lightning/issues/3683",
    "publishedAt": "2020-04-30T22:56:16Z",
    "title": "Expose a Channel's Routing Fee Setting via `listpeers`",
    "labels": [
      "json-rpc",
      "feature",
      "good first issue"
    ],
    "imageUrl": "https://avatars.githubusercontent.com/u/12729539?v=4"
  },
  {
    "url": "https://github.com/ElementsProject/lightning/issues/4043",
    "publishedAt": "2020-09-12T00:54:35Z",
    "title": "Time out on non-responsive opens",
    "labels": [
      "good first issue",
      "funding"
    ],
    "imageUrl": "https://avatars.githubusercontent.com/u/12729539?v=4"
  },
  {
    "url": "https://github.com/ElementsProject/lightning/issues/4720",
    "publishedAt": "2021-08-16T16:39:42Z",
    "title": "channel leases: restrict channel fee updates for leased channels to be less than committed rates",
    "labels": [
      "good first issue"
    ],
    "imageUrl": "https://avatars.githubusercontent.com/u/12729539?v=4"
  },
  {
    "url": "https://github.com/ElementsProject/lightning/issues/5127",
    "publishedAt": "2022-03-24T10:36:46Z",
    "title": "Allow setting fee limits on offerout",
    "labels": [
      "good first issue"
    ],
    "imageUrl": "https://avatars.githubusercontent.com/u/12729539?v=4"
  },
  {
    "url": "https://github.com/ElementsProject/lightning/issues/5390",
    "publishedAt": "2022-07-08T22:38:09Z",
    "title": "Turn on strict tables for SQLITE3 when running integration tests",
    "labels": [
      "testing",
      "good first issue"
    ],
    "imageUrl": "https://avatars.githubusercontent.com/u/12729539?v=4"
  },
  {
    "url": "https://github.com/ElementsProject/lightning/issues/5603",
    "publishedAt": "2022-09-18T17:27:56Z",
    "title": "`invoice_payment` hook doesn't get replayed when lightningd is restarted",
    "labels": [
      "good first issue"
    ],
    "imageUrl": "https://avatars.githubusercontent.com/u/12729539?v=4"
  },
  {
    "url": "https://github.com/ElementsProject/lightning/issues/6909",
    "publishedAt": "2023-11-30T08:44:16Z",
    "title": "Documentation of listsendpays",
    "labels": [
      "docs",
      "good first issue"
    ],
    "imageUrl": "https://avatars.githubusercontent.com/u/12729539?v=4"
  }
]